aissemble_universal_config_loader/config_loader.py
aissemble_universal_config_loader/ipython/config_helper.py
aissemble_universal_config_loader/util/utils.py
aissemble_universal_config_loader-0.1.0.dist-info/LICENSE.txt
aissemble_universal_config_loader-0.1.0.dist-info/METADATA
aissemble_universal_config_loader-0.1.0.dist-info/WHEEL
aissemble_universal_config_loader-0.1.0.dist-info/RECORD
