Metadata-Version: 2.3
Name: aissemble-universal-config-loader
Version: 0.1.0
Summary: aiSSEMBLE Universal Config Loader
License: Booz Allen Public License v1.0
Author: aiSSEMBLE Baseline Community
Author-email: aissemble@bah.com
Requires-Python: >=3.11.4
Classifier: License :: Other/Proprietary License
Classifier: Programming Language :: Python :: 3
Classifier: Programming Language :: Python :: 3.12
Classifier: Programming Language :: Python :: 3.13
Requires-Dist: ipython (>=9.3.0)
Requires-Dist: krausening (>=20)
Project-URL: Homepage, https://github.com/boozallen/aissemble-universal-config
